{
  "plus fort": 3,
  "pas droit": 3,
  "pas mal": 3,
  "pas rugueux": 2,
  "fr\u00e9quence pur": 2,
  "pas impulsif": 2,
  "assez rapide": 2,
  "son rugueux": 2,
  "pas lisse": 2,
  "pas propre": 2,
  "plus rugueux": 2,
  "instabilit\u00e9 spectral": 2,
  "plus simple": 2,
  "pas pur": 2,
  "plus m\u00e9dium": 2,
  "vibration forcer": 2,
  "micro temporel": 2,
  "petite modification": 2,
  "jouer propre": 2,
  "sinus pur": 2,
  "structure micro": 2,
  "vraiment rugueux": 2,
  "frotter rugueux": 1,
  "gratter attaquer": 1,
  "rugosit\u00e9 sachant": 1,
  "\u00e9criture orchestral": 1,
  "pas vibrer": 1,
  "presque bruiter": 1,
  "mati\u00e8re bruiter": 1,
  "\u00e9l\u00e9ment parasite": 1,
  "moins fin": 1,
  "peu brut": 1,
  "vachement rugueux": 1,
  "oppos\u00e9 totale": 1,
  "aspect organique": 1,
  "aspect rugueux": 1,
  "oeuvre orchestral": 1,
  "d\u00e9veloppement temporel": 1,
  "vue spectral": 1,
  "falloir jouer": 1,
  "pas souple": 1,
  "vouloir jouer": 1,
  "attaquer frott\u00e9e": 1,
  "assez fort": 1,
  "projet artistique": 1,
  "mati\u00e8re lisse": 1,
  "plus r\u00e9duire": 1,
  "assez homog\u00e8ne": 1,
  "timbre normal": 1,
  "orchestre jouer": 1,
  "jouer mal": 1,
  "saccader presque": 1,
  "mime 02": 1,
  "irr\u00e9gularit\u00e9 p\u00e9riodiquement": 1,
  "corde grave": 1,
  "non homog\u00e8ne": 1,
  "harmonique rugueux": 1,
  "purement r\u00e9sonant": 1,
  "contenu gestuel": 1,
  "battement variation": 1,
  "proprement musical": 1,
  "seul fr\u00e9quence": 1,
  "surface rugueux": 1,
  "peu in\u00e9gal": 1,
  "texture rugueux": 1,
  "variation fr\u00e9quentiel": 1,
  "musique int\u00e9ressant": 1,
  "frotte sensation": 1,
  "peu rugueux": 1,
  "composante tonal": 1,
  "rugueux irr\u00e9gulier": 1,
  "pas constant": 1,
  "air inerte": 1,
  "moins \u00e9l\u00e9gant": 1,
  "caisse claire": 1,
  "assez rapidement": 1,
  "moyen visuellement": 1,
  "usages traditionnel": 1,
  "r\u00e9flexion esth\u00e9tique": 1,
  "m\u00e9lange al\u00e9atoire": 1,
  "peu \u00e2pre": 1,
  "pas r\u00e9gulier": 1,
  "tactile rugueux": 1,
  "rugueux justement": 1,
  "r\u00e9sistance rugueux": 1,
  "peu enrouer": 1,
  "assez doux": 1,
  "coup rugueux": 1,
  "frottement forc\u00e9": 1,
  "daniel pressnitzer": 1,
  "mat\u00e9riau musical": 1,
  "composante concret": 1,
  "pas stable": 1,
  "qualit\u00e9 naturel": 1,
  "type similaire": 1,
  "consistance h\u00e9t\u00e9rog\u00e8ne": 1,
  "steve mcadams": 1,
  "mati\u00e8re rentre": 1,
  "effet \u00e9cras\u00e9": 1,
  "nuance important": 1,
  "aspect temporel": 1,
  "langage musical": 1,
  "bande critique": 1,
  "variation rapide": 1,
  "composante bruiter": 1,
  "ronde lisse": 1,
  "pas auditif": 1,
  "trop important": 1,
  "devenir fou": 1,
  "vibration agressive": 1,
  "petit grains": 1,
  "moins fine": 1,
  "rugosit\u00e9 devoir": 1,
  "granulation typique": 1,
  "composante purement": 1,
  "pas naturel": 1,
  "petit bruit": 1,
  "stimulus visuel": 1,
  "frotte ensemble": 1,
  "pas d\u00e9sagr\u00e9able": 1,
  "plus instable": 1,
  "sensation physique": 1,
  "mati\u00e8re brute": 1,
  "associerai rugosit\u00e9": 1,
  "plus souple": 1,
  "plan tactile": 1,
  "mati\u00e8re rugueux": 1,
  "rugosit\u00e9 opposition": 1,
  "\u00e9ponge gris": 1,
  "frrrrr effectivement": 1,
  "moins important": 1,
  "peu agressif": 1,
  "partie prenant": 1,
  "mati\u00e8re lorsqu": 1,
  "pas jouer": 1,
  "variation al\u00e9atoire": 1,
  "assez instable": 1,
  "die soldaten": 1,
  "rond justement": 1,
  "02 39": 1,
  "plus agressif": 1,
  "composante souffler": 1,
  "composante rugueux": 1,
  "origine naturel": 1,
  "composante int\u00e9grant": 1,
  "micro information": 1,
  "pas homog\u00e8ne": 1,
  "plan temporel": 1,
  "plus aigu": 1,
  "bonne image": 1,
  "seconde mineur": 1,
  "grain moyen": 1,
  "homog\u00e8ne spectralement": 1,
  "dispositif symphonique": 1,
  "son bouch\u00e9": 1,
  "irr\u00e9gularit\u00e9 temporel": 1,
  "percussion type": 1,
  "vitesse donne": 1,
  "pas rond": 1,
  "rugosit\u00e9 psychoacoustique": 1,
  "folle activit\u00e9": 1,
  "d\u00e9former professionnellement": 1,
  "unit\u00e9 successif": 1,
  "amplitude rapide": 1,
  "plus brut": 1,
  "vite heu": 1,
  "vouloir cr\u00e9er": 1,
  "gros caillou": 1,
  "pas agressif": 1,
  "lire sensible": 1,
  "fr\u00e9quentiel mime": 1,
  "bouge vite": 1,
  "peu granuleux": 1,
  "archet gratte": 1,
  "aspect impr\u00e9visible": 1,
  "vraiment partir": 1,
  "m\u00e9dium aigu": 1,
  "pouvoir lisser": 1,
  "dynamique it\u00e9ratif": 1,
  "petite asp\u00e9rit\u00e9": 1,
  "pas pr\u00e9visible": 1,
  "trop entretenu": 1,
  "sans doute": 1,
  "synth\u00e8se granulaire": 1,
  "appelle rugosit\u00e9": 1,
  "assez bruiter": 1,
  "plus r\u00e9gulier": 1,
  "galet rugueux": 1,
  "plus sauvage": 1,
  "pas p\u00e9riodique": 1,
  "rugosit\u00e9 arracher": 1,
  "peu bruiter": 1,
  "non lisse": 1,
  "son rond": 1,
  "type peigne": 1,
  "type percussif": 1,
  "moins pur": 1,
  "assez continu": 1,
  "rugueux \u00e9voque": 1,
  "pas m\u00fbr": 1,
  "moins propre": 1,
  "symphonique traditionnel": 1,
  "plus complexe": 1
}